dqrobotics/__init__.py
dqrobotics/_dqrobotics.cpython-311-darwin.so
dqrobotics/interfaces/__init__.py
dqrobotics/interfaces/coppeliasim/__init__.py
dqrobotics/interfaces/json11/__init__.py
dqrobotics/interfaces/vrep/__init__.py
dqrobotics/interfaces/vrep/robots/__init__.py
dqrobotics/robot_control/__init__.py
dqrobotics/robot_modeling/__init__.py
dqrobotics/robots/__init__.py
dqrobotics/solvers/__init__.py
dqrobotics/solvers/_dq_cplex_solver.py
dqrobotics/solvers/_dq_quadprog_solver.py
dqrobotics/utils/__init__.py
dqrobotics/utils/DQ_LinearAlgebra/__init__.py
dqrobotics/utils/DQ_Math/__init__.py
dqrobotics-25.4.0.dist-info/LICENSE
dqrobotics-25.4.0.dist-info/METADATA
dqrobotics-25.4.0.dist-info/WHEEL
dqrobotics-25.4.0.dist-info/top_level.txt
dqrobotics-25.4.0.dist-info/RECORD
